scruft/__init__.py
scruft/__main__.py
scruft/_cli.py
scruft/_version.py
scruft/exceptions.py
scruft/py.typed
scruft/_commands/__init__.py
scruft/_commands/check.py
scruft/_commands/create.py
scruft/_commands/diff.py
scruft/_commands/link.py
scruft/_commands/update.py
scruft/_commands/utils/__init__.py
scruft/_commands/utils/cookiecutter.py
scruft/_commands/utils/cruft.py
scruft/_commands/utils/diff.py
scruft/_commands/utils/generate.py
scruft/_commands/utils/iohelper.py
scruft-0.2.1.dist-info/licenses/LICENSE
scruft-0.2.1.dist-info/METADATA
scruft-0.2.1.dist-info/WHEEL
scruft-0.2.1.dist-info/entry_points.txt
scruft-0.2.1.dist-info/top_level.txt
scruft-0.2.1.dist-info/RECORD
